doorget/CacheKey.py
doorget/DiskStorage.py
doorget/IdentityStorage.py
doorget/MemoryStorage.py
doorget/Storage.py
doorget/StorageContainer.py
doorget/StorageMode.py
doorget/__init__.py
doorget/cache.py
doorget/constants.py
doorget/doorget.py
doorget-1.1.dist-info/LICENSE
doorget-1.1.dist-info/METADATA
doorget-1.1.dist-info/WHEEL
doorget-1.1.dist-info/top_level.txt
doorget-1.1.dist-info/RECORD
