Metadata-Version: 2.1
Name: doorget
Version: 1.1
Summary: Memoize package supporting data dependencies
Author-email: Fabien Dieulle <fabien.dieull@hotmail.fr>
Project-URL: Homepage, https://github.com/fdieulle/doorget
Project-URL: Issues, https://github.com/fdieulle/doorget/issues
Keywords: memoize,memoization,doorget
Classifier: Programming Language :: Python :: 3
Classifier: License :: OSI Approved :: MIT License
Classifier: Operating System :: OS Independent
Requires-Python: >=3.6
License-File: LICENSE
Requires-Dist: pandas
Requires-Dist: pyarrow
